odoo10_addon_connector_magento_customize_example-10.0.1.0.0-py2.7-nspkg.pth
odoo/addons/connector_magento_customize_example/README.rst
odoo/addons/connector_magento_customize_example/__init__.py
odoo/addons/connector_magento_customize_example/__manifest__.py
odoo/addons/connector_magento_customize_example/i18n/de.po
odoo/addons/connector_magento_customize_example/i18n/es.po
odoo/addons/connector_magento_customize_example/i18n/fr.po
odoo/addons/connector_magento_customize_example/i18n/it.po
odoo/addons/connector_magento_customize_example/i18n/nl.po
odoo/addons/connector_magento_customize_example/i18n/sl.po
odoo/addons/connector_magento_customize_example/models/__init__.py
odoo/addons/connector_magento_customize_example/models/partner.py
odoo10_addon_connector_magento_customize_example-10.0.1.0.0.dist-info/DESCRIPTION.rst
odoo10_addon_connector_magento_customize_example-10.0.1.0.0.dist-info/METADATA
odoo10_addon_connector_magento_customize_example-10.0.1.0.0.dist-info/RECORD
odoo10_addon_connector_magento_customize_example-10.0.1.0.0.dist-info/WHEEL
odoo10_addon_connector_magento_customize_example-10.0.1.0.0.dist-info/metadata.json
odoo10_addon_connector_magento_customize_example-10.0.1.0.0.dist-info/namespace_packages.txt
odoo10_addon_connector_magento_customize_example-10.0.1.0.0.dist-info/top_level.txt
